reliable_finalizer/__init__.py
reliable_finalizer-1.0.0.dist-info/LICENSE
reliable_finalizer-1.0.0.dist-info/METADATA
reliable_finalizer-1.0.0.dist-info/WHEEL
reliable_finalizer-1.0.0.dist-info/top_level.txt
reliable_finalizer-1.0.0.dist-info/RECORD
