Metadata-Version: 2.1
Name: reliable-finalizer
Version: 1.0.0
Summary: Python utility for creation of reliable finalizer as an alternative to __del__ method
Home-page: https://github.com/TimurTimergalin/reliable-finalizer
Author: TimurTimergalin
Author-email: tmtimergalin8080@gmail.com
Keywords: python finalize
Classifier: Programming Language :: Python
Classifier: License :: OSI Approved :: MIT License
Classifier: Operating System :: OS Independent
Requires-Python: >=3.2
License-File: LICENSE
